advanced_python_singleton/__init__.py
advanced_python_singleton/singleton.py
advanced_python_singleton/ttlsingleton.py
advanced_python_singleton-1.3.2.dist-info/METADATA
advanced_python_singleton-1.3.2.dist-info/WHEEL
advanced_python_singleton-1.3.2.dist-info/top_level.txt
advanced_python_singleton-1.3.2.dist-info/RECORD
