Metadata-Version: 2.1
Name: advanced-python-singleton
Version: 1.3.2
Summary: Singleton & TtlSingleton meta-class
Home-page: https://github.com/jogakdal/advanced-singleton
Author: 황용호
Author-email: jogakdal@gmail.com
License: UNKNOWN
Keywords: jogakdal,Singleton,TTL,metaclass
Platform: UNKNOWN
Classifier: Programming Language :: Python :: 3
Classifier: Operating System :: OS Independent
Requires-Python: >=3.6
Requires-Dist: expiringdict
